{
	"configurations" : 
	[
		{
			"directories" : 
			[
				{
					"build" : ".",
					"childIndexes" : 
					[
						1
					],
					"hasInstallRule" : true,
					"jsonFile" : "directory-.-f5ebdc15457944623624.json",
					"projectIndex" : 0,
					"source" : "."
				},
				{
					"build" : "lib",
					"hasInstallRule" : true,
					"jsonFile" : "directory-lib-6b82f329fac8b0491358.json",
					"parentIndex" : 0,
					"projectIndex" : 0,
					"source" : "lib",
					"targetIndexes" : 
					[
						0,
						1
					]
				}
			],
			"name" : "",
			"projects" : 
			[
				{
					"directoryIndexes" : 
					[
						0,
						1
					],
					"name" : "HELLOLIB",
					"targetIndexes" : 
					[
						0,
						1
					]
				}
			],
			"targets" : 
			[
				{
					"directoryIndex" : 1,
					"id" : "hello::@306ed2d68c6501e8728f",
					"jsonFile" : "target-hello-5cdb00c1a7618aff7e19.json",
					"name" : "hello",
					"projectIndex" : 0
				},
				{
					"directoryIndex" : 1,
					"id" : "hello_static::@306ed2d68c6501e8728f",
					"jsonFile" : "target-hello_static-02f1de4962d16122e93f.json",
					"name" : "hello_static",
					"projectIndex" : 0
				}
			]
		}
	],
	"kind" : "codemodel",
	"paths" : 
	{
		"build" : "/home/bupo/my_study/slam14/slam14_my/cap2/cmake_study/t3/build",
		"source" : "/home/bupo/my_study/slam14/slam14_my/cap2/cmake_study/t3"
	},
	"version" : 
	{
		"major" : 2,
		"minor" : 4
	}
}
