{
	"configurations" : 
	[
		{
			"directories" : 
			[
				{
					"build" : ".",
					"jsonFile" : "directory-.-Release-f5ebdc15457944623624.json",
					"minimumCMakeVersion" : 
					{
						"string" : "2.8"
					},
					"projectIndex" : 0,
					"source" : ".",
					"targetIndexes" : 
					[
						0,
						1
					]
				}
			],
			"name" : "Release",
			"projects" : 
			[
				{
					"directoryIndexes" : 
					[
						0
					],
					"name" : "bundle_adjustment_ceres",
					"targetIndexes" : 
					[
						0,
						1
					]
				}
			],
			"targets" : 
			[
				{
					"directoryIndex" : 0,
					"id" : "bal_common::@6890427a1f51a3e7e1df",
					"jsonFile" : "target-bal_common-Release-1061c6c046acb12f58e1.json",
					"name" : "bal_common",
					"projectIndex" : 0
				},
				{
					"directoryIndex" : 0,
					"id" : "bundle_adjustment_ceres::@6890427a1f51a3e7e1df",
					"jsonFile" : "target-bundle_adjustment_ceres-Release-78f9953ec1a8c32f7204.json",
					"name" : "bundle_adjustment_ceres",
					"projectIndex" : 0
				}
			]
		}
	],
	"kind" : "codemodel",
	"paths" : 
	{
		"build" : "/home/bupo/my_study/slam14/slam14_my/cap9/bundle_adjustment_ceres/cmake-build-release",
		"source" : "/home/bupo/my_study/slam14/slam14_my/cap9/bundle_adjustment_ceres"
	},
	"version" : 
	{
		"major" : 2,
		"minor" : 3
	}
}
